piwave/__init__.py
piwave/__main__.py
piwave/logger.py
piwave/piwave.py
piwave/backends/__init__.py
piwave/backends/base.py
piwave/backends/fm_transmitter.py
piwave/backends/pi_fm_rds.py
piwave-2.1.11.dist-info/licenses/LICENSE
piwave-2.1.11.dist-info/METADATA
piwave-2.1.11.dist-info/WHEEL
piwave-2.1.11.dist-info/top_level.txt
piwave-2.1.11.dist-info/RECORD
