Metadata-Version: 2.4
Name: piwave
Version: 2.1.11
Summary: A python module to broadcast radio waves with your Raspberry Pi.
Home-page: https://github.com/douxxtech/piwave
Author: Douxx
Author-email: douxx@douxx.tech
License: GPL-3.0-or-later
Project-URL: Bug Reports, https://github.com/douxxtech/piwave/issues
Project-URL: Source, https://github.com/douxxtech/piwave
Keywords: raspberry pi,radio,fm,rds,streaming,audio,broadcast
Classifier: Development Status :: 5 - Production/Stable
Classifier: Intended Audience :: Developers
Classifier: Topic :: Software Development :: Libraries :: Python Modules
Classifier: Programming Language :: Python :: 3
Classifier: License :: OSI Approved :: GNU General Public License v3 (GPLv3)
Classifier: Operating System :: POSIX :: Linux
Requires-Python: >=3.7
License-File: LICENSE
Requires-Dist: dlogger==1.0.4
Provides-Extra: dev
Requires-Dist: pytest>=6.0; extra == "dev"
Requires-Dist: pytest-cov>=2.0; extra == "dev"
Requires-Dist: black>=22.0; extra == "dev"
Requires-Dist: flake8>=4.0; extra == "dev"
Dynamic: license-file
